js_script_py/__init__.py
js_script_py/setup.py
js_script_py-1.8.dist-info/METADATA
js_script_py-1.8.dist-info/WHEEL
js_script_py-1.8.dist-info/top_level.txt
js_script_py-1.8.dist-info/RECORD
