Metadata-Version: 2.1
Name: js-script-py
Version: 1.8
Summary: Turn python code to javascript code
Home-page: https://repl.it/@Downey/pythonjavascript
Author: Stark.-12x_42
Author-email: xsumagravity@gmail.com
License: UNKNOWN
Platform: UNKNOWN
Classifier: Programming Language :: Python :: 3
Classifier: License :: OSI Approved :: MIT License
Classifier: Operating System :: MacOS
Requires-Python: >=3.6
